fmd5sum/__init__.py
fmd5sum/fmd5sum.py
fmd5sum-0.1.0.dist-info/METADATA
fmd5sum-0.1.0.dist-info/WHEEL
fmd5sum-0.1.0.dist-info/entry_points.txt
fmd5sum-0.1.0.dist-info/top_level.txt
fmd5sum-0.1.0.dist-info/RECORD
