Metadata-Version: 2.1
Name: fmd5sum
Version: 0.1.0
Summary: A faster MD5 sum calculator that uses concurrency.
Author: Your Name
Classifier: Development Status :: 3 - Alpha
Classifier: Intended Audience :: Developers
Classifier: Natural Language :: English
Classifier: Programming Language :: Python :: 3
Classifier: Programming Language :: Python :: 3.6
Classifier: Programming Language :: Python :: 3.7
Classifier: Programming Language :: Python :: 3.8
Classifier: Programming Language :: Python :: 3.9
Requires-Dist: concurrent-futures ; python_version < "3.2"
